LICENSE
MANIFEST.in
README.md
pyproject.toml
setup.py
src/haversine_distance/__init__.py
src/haversine_distance/haversine.c
src/haversine_distance/haversine.pyx
src/haversine_distance.egg-info/PKG-INFO
src/haversine_distance.egg-info/SOURCES.txt
src/haversine_distance.egg-info/dependency_links.txt
src/haversine_distance.egg-info/top_level.txt