Metadata-Version: 2.4
Name: haversine-distance
Version: 0.1.0
Summary: Fast haversine distance calculation using Cython
Author-email: Artem Lykhvar <me@a10r.com>
License-Expression: MIT
Project-URL: Documentation, https://github.com/lykhvar/haversine-distance#readme
Project-URL: Issues, https://github.com/lykhvar/haversine-distance/issues
Project-URL: Source, https://github.com/lykhvar/haversine-distance
Keywords: haversine,distance,geodetic,gps,geospatial,Cython,GIS
Classifier: Development Status :: 4 - Beta
Classifier: Programming Language :: Python
Classifier: Programming Language :: Python :: 3.9
Classifier: Programming Language :: Python :: 3.10
Classifier: Programming Language :: Python :: 3.11
Classifier: Programming Language :: Python :: 3.12
Classifier: Programming Language :: Python :: 3.13
Classifier: Programming Language :: Python :: 3.14
Requires-Python: >=3.9
License-File: LICENSE
Dynamic: license-file
